pytest_rmysql/__init__.py
pytest_rmysql/config.py
pytest_rmysql/plugin.py
pytest_rmysql-0.1.6.dist-info/entry_points.txt
pytest_rmysql-0.1.6.dist-info/METADATA
pytest_rmysql-0.1.6.dist-info/WHEEL
pytest_rmysql-0.1.6.dist-info/RECORD
